seventilation_client/__init__.py
seventilation_client/api_client.py
seventilation_client/configuration.py
seventilation_client/rest.py
seventilation_client/api/__init__.py
seventilation_client/api/areas_api.py
seventilation_client/api/controller_api.py
seventilation_client/api/devices_api.py
seventilation_client/api/gateway_api.py
seventilation_client/api/notifications_api.py
seventilation_client/api/settings_api.py
seventilation_client/api/setup_api.py
seventilation_client/api/telemetry_api.py
seventilation_client/api/users_api.py
seventilation_client/models/__init__.py
seventilation_client/models/analog_input.py
seventilation_client/models/analog_input_curve_parameters.py
seventilation_client/models/analog_input_curve_parameters_x.py
seventilation_client/models/analog_input_curve_parameters_y_fanlevel.py
seventilation_client/models/analog_input_curve_parameters_y_humidity.py
seventilation_client/models/analog_input_curve_parameters_y_temp.py
seventilation_client/models/analog_input_curve_parameters_yco2.py
seventilation_client/models/area.py
seventilation_client/models/area_timers.py
seventilation_client/models/areas.py
seventilation_client/models/areas_label_body.py
seventilation_client/models/areas_mode_body.py
seventilation_client/models/areas_timeprogram_body.py
seventilation_client/models/boost_mode.py
seventilation_client/models/controller.py
seventilation_client/models/device.py
seventilation_client/models/devicesidsettingsfilter_filter.py
seventilation_client/models/digital_input.py
seventilation_client/models/digital_input_areas.py
seventilation_client/models/digital_output.py
seventilation_client/models/error.py
seventilation_client/models/error_areas_errors.py
seventilation_client/models/error_settings_errors.py
seventilation_client/models/error_setup_errors.py
seventilation_client/models/filter.py
seventilation_client/models/gateway.py
seventilation_client/models/id_name_body.py
seventilation_client/models/inline_response200.py
seventilation_client-0.1.0.dist-info/LICENSE
seventilation_client-0.1.0.dist-info/METADATA
seventilation_client-0.1.0.dist-info/WHEEL
seventilation_client-0.1.0.dist-info/top_level.txt
seventilation_client-0.1.0.dist-info/RECORD
