Metadata-Version: 2.1
Name: seventilation-client
Version: 0.1.0
Summary: SEC Smart API
Home-page: https://github.com/epiehl/seventilation-client.git
Author-email: 
Keywords: Swagger,SEC Smart API
License-File: LICENSE
Requires-Dist: urllib3 >=1.15
Requires-Dist: six >=1.10
Requires-Dist: certifi
Requires-Dist: python-dateutil
